[
    {
     "Timestamp": null,
     "name": null,
     "address": null,
     "image url": null,
     "Organizational Unit": null,
     "Position": null
    },
    {
     "Timestamp": null,
     "name": null,
     "address": null,
     "image url": null,
     "Organizational Unit": null,
     "Position": null
    },
    {
     "Timestamp": null,
     "name": null,
     "address": null,
     "image url": null,
     "Organizational Unit": null,
     "Position": null
    },
    {
     "Timestamp": "5\/9\/2022 20:06:14",
     "name": "Sami",
     "address": "0xf39Fd6e51aad88F6F4ce6aB8827279cffFb92266",
     "image url": "https:\/\/cdn.britannica.com\/62\/192062-131-96B933EF\/mug-shot-Colombia-control-agency-Medellin.jpg",
     "Organizational Unit": 0,
     "Position": 0
    }
   ]